majis/__init__.py
majis/__version__.py
majis/itl/__init__.py
majis/itl/cli.py
majis/itl/export.py
majis/itl/reader.py
majis/itl/timeline.py
majis/itl/timeline.xlsm
majis/itl/csv/__init__.py
majis/itl/csv/export.py
majis/itl/eps/__init__.py
majis/itl/eps/export.py
majis/itl/eps/reader.py
majis/itl/json/__init__.py
majis/itl/json/export.py
majis/itl/json/mapping.py
majis/itl/json/reader.py
majis/misc/__init__.py
majis/misc/depreciation.py
majis/misc/events.py
majis/misc/evf.py
majis/misc/export.py
majis/misc/time.py
majis/opl/__init__.py
majis/opl/convert.py
majis/opl/export.py
majis/opl/reader.py
majis/schema/__init__.py
majis/schema/jsoc-itl-schema.json
majis/schema/jsoc-opl-schema.json
majis/schema/majis-itl-schema.json
majis/schema/schema.py
majis_ops-1.2.2.dist-info/METADATA
majis_ops-1.2.2.dist-info/WHEEL
majis_ops-1.2.2.dist-info/entry_points.txt
majis_ops-1.2.2.dist-info/licenses/LICENSE.md
majis_ops-1.2.2.dist-info/RECORD
