Metadata-Version: 2.4
Name: majis-ops
Version: 1.2.2
Summary: Juice/MAJIS operations toolbox
Project-URL: Source, https://git.ias.u-psud.fr/majis_sgs/operations/majis-ops-toolbox
Project-URL: Issues, https://git.ias.u-psud.fr/majis_sgs/operations/majis-ops-toolbox/-/issues
Project-URL: Documentation, https://majis-ops.readthedocs.io/en/latest/
Author: Axelle Gottafray
Author-email: Benoît Seignovert <benoit.seignovert@univ-nantes.fr>, Nicolas Manaud <nicolas@spacefrog.design>
Maintainer-email: Benoît Seignovert <benoit.seignovert@univ-nantes.fr>
License-Expression: BSD-3-Clause
License-File: LICENSE.md
Keywords: esa,ias,juice,majis
Classifier: Development Status :: 5 - Production/Stable
Classifier: Programming Language :: Python
Classifier: Programming Language :: Python :: 3.10
Classifier: Programming Language :: Python :: 3.11
Classifier: Programming Language :: Python :: 3.12
Requires-Python: >=3.10
Requires-Dist: jsonschema>=4.25
Requires-Dist: numpy>=1.26
Requires-Dist: openpyxl>=3.1.3
Requires-Dist: packaging>=24
Requires-Dist: planetary-coverage>=1.1
